caravel/__init__.py
caravel/configure.py
caravel/info.py
caravel/io.py
caravel/mail.py
caravel/parser.py
caravel/utils.py
caravel/validation.py
caravel/loaders/__init__.py
caravel/loaders/_csv.py
caravel/loaders/_dwi.py
caravel/loaders/_edf.py
caravel/loaders/_json.py
caravel/loaders/_mp4.py
caravel/loaders/_mzml.py
caravel/loaders/_nifti.py
caravel/loaders/_pdf.py
caravel/loaders/_plink.py
caravel/loaders/_png.py
caravel/loaders/_targz.py
caravel/loaders/_tsv.py
caravel/loaders/_vcf.py
caravel/loaders/_xlsx.py
caravel/loaders/loader_base.py
caravel/nextcloud/__init__.py
caravel/nextcloud/base.py
caravel/nextcloud/nextcloud.py
caravel/nextcloud/requester.py
caravel/nextcloud/response.py
caravel/nextcloud/api_wrappers/__init__.py
caravel/nextcloud/api_wrappers/activity.py
caravel/nextcloud/api_wrappers/apps.py
caravel/nextcloud/api_wrappers/capabilities.py
caravel/nextcloud/api_wrappers/federated_cloudshares.py
caravel/nextcloud/api_wrappers/forms.py
caravel/nextcloud/api_wrappers/group.py
caravel/nextcloud/api_wrappers/group_folders.py
caravel/nextcloud/api_wrappers/notifications.py
caravel/nextcloud/api_wrappers/share.py
caravel/nextcloud/api_wrappers/user.py
caravel/nextcloud/api_wrappers/user_ldap.py
caravel/nextcloud/api_wrappers/webdav.py
caravel/parsers/__init__.py
caravel/parsers/bids.py
caravel/parsers/parser_base.py
pycaravel-1.0.0.data/scripts/project-ci
pycaravel-1.0.0.dist-info/METADATA
pycaravel-1.0.0.dist-info/WHEEL
pycaravel-1.0.0.dist-info/top_level.txt
pycaravel-1.0.0.dist-info/RECORD
