Metadata-Version: 2.1
Name: pycaravel
Version: 1.0.0
Author-email: pycaravel developers <antoine.grigis@cea.fr>
License: CeCILL-B
Project-URL: Source, https://github.com/neurospincloud-ci/pycaravel/hopla
Project-URL: Tracker, https://github.com/neurospincloud-ci/pycaravel/issues
Platform: Linux
Platform: OSX
Classifier: Development Status :: 1 - Planning
Classifier: Environment :: Console
Classifier: Operating System :: OS Independent
Classifier: Programming Language :: Python
Classifier: Topic :: Scientific/Engineering
Requires-Python: >=3.8
Requires-Dist: pandas
Requires-Dist: nibabel
Requires-Dist: numpy
Requires-Dist: imageio[ffmpeg]
Requires-Dist: PyPDF2
Requires-Dist: vcfpy
Requires-Dist: pandas-plink
Requires-Dist: pyEDFlib
Requires-Dist: requests
Requires-Dist: python-docx
Requires-Dist: fire
Requires-Dist: pymzml
